newstrends/__init__.py
newstrends/_nbdev.py
newstrends/describe.py
newstrends/download.py
newstrends/loader.py
newstrends/predict.py
newstrends/visualize.py
newstrends-0.0.15.dist-info/LICENSE
newstrends-0.0.15.dist-info/METADATA
newstrends-0.0.15.dist-info/WHEEL
newstrends-0.0.15.dist-info/entry_points.txt
newstrends-0.0.15.dist-info/top_level.txt
newstrends-0.0.15.dist-info/RECORD
